kiarina/utils/encoding/__init__.py
kiarina/utils/encoding/py.typed
kiarina/utils/encoding/settings.py
kiarina/utils/encoding/_helpers/__init__.py
kiarina/utils/encoding/_helpers/decode_binary_to_text.py
kiarina/utils/encoding/_helpers/detect_encoding.py
kiarina/utils/encoding/_helpers/get_default_encoding.py
kiarina/utils/encoding/_helpers/is_binary.py
kiarina/utils/encoding/_operations/__init__.py
kiarina/utils/encoding/_operations/detect_with_charset_normalizer.py
kiarina/utils/encoding/_operations/detect_with_fallback.py
kiarina/utils/encoding/_operations/detect_with_nkf.py
kiarina/utils/encoding/_operations/should_use_nkf.py
kiarina/utils/encoding/_utils/__init__.py
kiarina/utils/encoding/_utils/normalize_newlines.py
kiarina/utils/ext/__init__.py
kiarina/utils/ext/py.typed
kiarina/utils/ext/settings.py
kiarina/utils/ext/_helpers/__init__.py
kiarina/utils/ext/_helpers/detect_extension.py
kiarina/utils/ext/_helpers/extract_extension.py
kiarina/utils/ext/_operations/__init__.py
kiarina/utils/ext/_operations/detect_with_dictionary.py
kiarina/utils/ext/_operations/detect_with_mimetypes.py
kiarina/utils/ext/_operations/extract_multi_extension.py
kiarina/utils/ext/_utils/__init__.py
kiarina/utils/ext/_utils/clean_url_path.py
kiarina/utils/ext/_utils/normalize_extension.py
kiarina/utils/ext/_utils/normalize_mime_type.py
kiarina/utils/file/__init__.py
kiarina/utils/file/asyncio.py
kiarina/utils/file/py.typed
kiarina/utils/file/settings.py
kiarina/utils/file/_async/__init__.py
kiarina/utils/file/_async/helpers/__init__.py
kiarina/utils/file/_async/helpers/read_file.py
kiarina/utils/file/_async/helpers/read_markdown.py
kiarina/utils/file/_async/helpers/write_file.py
kiarina/utils/file/_async/utils/__init__.py
kiarina/utils/file/_async/utils/read_binary.py
kiarina/utils/file/_async/utils/read_json_dict.py
kiarina/utils/file/_async/utils/read_json_list.py
kiarina/utils/file/_async/utils/read_text.py
kiarina/utils/file/_async/utils/read_yaml_dict.py
kiarina_utils_file-1.35.0.dist-info/METADATA
kiarina_utils_file-1.35.0.dist-info/WHEEL
kiarina_utils_file-1.35.0.dist-info/top_level.txt
kiarina_utils_file-1.35.0.dist-info/RECORD
