Metadata-Version: 2.4
Name: kiarina-utils-file
Version: 1.35.0
Summary: Comprehensive Python library for file I/O operations with automatic encoding detection, MIME type detection, and support for various file formats
Author-email: kiarina <kiarinadawa@gmail.com>
Maintainer-email: kiarina <kiarinadawa@gmail.com>
License-Expression: MIT
Project-URL: Homepage, https://github.com/kiarina/kiarina-python
Project-URL: Repository, https://github.com/kiarina/kiarina-python
Project-URL: Issues, https://github.com/kiarina/kiarina-python/issues
Project-URL: Changelog, https://github.com/kiarina/kiarina-python/blob/main/packages/kiarina-utils-file/CHANGELOG.md
Project-URL: Documentation, https://github.com/kiarina/kiarina-python/tree/main/packages/kiarina-utils-file#readme
Keywords: file,io,encoding,mime,async,sync,json,yaml,binary,text,detection,blob,atomic,thread-safe
Classifier: Development Status :: 4 - Beta
Classifier: Intended Audience :: Developers
Classifier: Operating System :: OS Independent
Classifier: Programming Language :: Python :: 3
Classifier: Programming Language :: Python :: 3.12
Classifier: Programming Language :: Python :: 3.13
Classifier: Topic :: Software Development :: Libraries :: Python Modules
Classifier: Topic :: System :: Filesystems
Classifier: Topic :: Text Processing
Classifier: Topic :: Utilities
Classifier: Typing :: Typed
Requires-Python: >=3.12
Requires-Dist: aiofiles>=24.1.0
Requires-Dist: charset-normalizer>=3.4.3
Requires-Dist: filelock>=3.19.1
Requires-Dist: pydantic>=2.11.7
Requires-Dist: pydantic-settings>=2.10.1
Requires-Dist: pydantic-settings-manager>=2.3.0
Requires-Dist: pyyaml>=6.0.2
